{"jobName":"mix193_original_1","accountId":"821883008341","results":{"transcripts":[{"transcript":"You start to wonder, well what am I going to teach them, What what do I want them to know and?"}],"items":[{"start_time":"0.24","end_time":"0.44","alternatives":[{"confidence":"1.0","content":"You"}],"type":"pronunciation"},{"start_time":"0.44","end_time":"0.66","alternatives":[{"confidence":"1.0","content":"start"}],"type":"pronunciation"},{"start_time":"0.66","end_time":"0.76","alternatives":[{"confidence":"1.0","content":"to"}],"type":"pronunciation"},{"start_time":"0.76","end_time":"1.03","alternatives":[{"confidence":"1.0","content":"wonder"}],"type":"pronunciation"},{"alternatives":[{"confidence":"0.0","content":","}],"type":"punctuation"},{"start_time":"1.03","end_time":"1.24","alternatives":[{"confidence":"0.9993","content":"well"}],"type":"pronunciation"},{"start_time":"1.24","end_time":"1.39","alternatives":[{"confidence":"1.0","content":"what"}],"type":"pronunciation"},{"start_time":"1.39","end_time":"1.49","alternatives":[{"confidence":"1.0","content":"am"}],"type":"pronunciation"},{"start_time":"1.49","end_time":"1.61","alternatives":[{"confidence":"1.0","content":"I"}],"type":"pronunciation"},{"start_time":"1.62","end_time":"1.86","alternatives":[{"confidence":"0.9817","content":"going"}],"type":"pronunciation"},{"start_time":"1.86","end_time":"1.93","alternatives":[{"confidence":"0.9817","content":"to"}],"type":"pronunciation"},{"start_time":"1.93","end_time":"2.34","alternatives":[{"confidence":"1.0","content":"teach"}],"type":"pronunciation"},{"start_time":"2.34","end_time":"2.67","alternatives":[{"confidence":"1.0","content":"them"}],"type":"pronunciation"},{"alternatives":[{"confidence":"0.0","content":","}],"type":"punctuation"},{"start_time":"2.67","end_time":"3.05","alternatives":[{"confidence":"1.0","content":"What"}],"type":"pronunciation"},{"start_time":"3.06","end_time":"3.63","alternatives":[{"confidence":"1.0","content":"what"}],"type":"pronunciation"},{"start_time":"3.64","end_time":"3.87","alternatives":[{"confidence":"1.0","content":"do"}],"type":"pronunciation"},{"start_time":"3.87","end_time":"3.97","alternatives":[{"confidence":"1.0","content":"I"}],"type":"pronunciation"},{"start_time":"3.97","end_time":"4.28","alternatives":[{"confidence":"1.0","content":"want"}],"type":"pronunciation"},{"start_time":"4.28","end_time":"4.44","alternatives":[{"confidence":"1.0","content":"them"}],"type":"pronunciation"},{"start_time":"4.44","end_time":"4.6","alternatives":[{"confidence":"1.0","content":"to"}],"type":"pronunciation"},{"start_time":"4.6","end_time":"5.1","alternatives":[{"confidence":"0.9984","content":"know"}],"type":"pronunciation"},{"start_time":"5.1","end_time":"5.36","alternatives":[{"confidence":"1.0","content":"and"}],"type":"pronunciation"},{"alternatives":[{"confidence":"0.0","content":"?"}],"type":"punctuation"}]},"status":"COMPLETED"}