{"jobName":"mix160_original_2","accountId":"821883008341","results":{"transcripts":[{"transcript":"Woman out there to please hear my words, we've got to stop this man, He will keep doing it."}],"items":[{"start_time":"0.0","end_time":"0.3","alternatives":[{"confidence":"0.9872","content":"Woman"}],"type":"pronunciation"},{"start_time":"0.3","end_time":"0.51","alternatives":[{"confidence":"1.0","content":"out"}],"type":"pronunciation"},{"start_time":"0.51","end_time":"0.71","alternatives":[{"confidence":"0.9994","content":"there"}],"type":"pronunciation"},{"start_time":"0.71","end_time":"0.85","alternatives":[{"confidence":"0.5979","content":"to"}],"type":"pronunciation"},{"start_time":"0.85","end_time":"1.45","alternatives":[{"confidence":"1.0","content":"please"}],"type":"pronunciation"},{"start_time":"1.45","end_time":"1.65","alternatives":[{"confidence":"0.9971","content":"hear"}],"type":"pronunciation"},{"start_time":"1.65","end_time":"1.84","alternatives":[{"confidence":"1.0","content":"my"}],"type":"pronunciation"},{"start_time":"1.84","end_time":"2.51","alternatives":[{"confidence":"1.0","content":"words"}],"type":"pronunciation"},{"alternatives":[{"confidence":"0.0","content":","}],"type":"punctuation"},{"start_time":"2.94","end_time":"3.29","alternatives":[{"confidence":"0.9968","content":"we've"}],"type":"pronunciation"},{"start_time":"3.29","end_time":"3.52","alternatives":[{"confidence":"0.9686","content":"got"}],"type":"pronunciation"},{"start_time":"3.52","end_time":"3.62","alternatives":[{"confidence":"0.9686","content":"to"}],"type":"pronunciation"},{"start_time":"3.62","end_time":"4.14","alternatives":[{"confidence":"1.0","content":"stop"}],"type":"pronunciation"},{"start_time":"4.14","end_time":"4.39","alternatives":[{"confidence":"1.0","content":"this"}],"type":"pronunciation"},{"start_time":"4.39","end_time":"5.06","alternatives":[{"confidence":"1.0","content":"man"}],"type":"pronunciation"},{"alternatives":[{"confidence":"0.0","content":","}],"type":"punctuation"},{"start_time":"5.44","end_time":"5.65","alternatives":[{"confidence":"1.0","content":"He"}],"type":"pronunciation"},{"start_time":"5.65","end_time":"5.8","alternatives":[{"confidence":"1.0","content":"will"}],"type":"pronunciation"},{"start_time":"5.8","end_time":"6.06","alternatives":[{"confidence":"1.0","content":"keep"}],"type":"pronunciation"},{"start_time":"6.06","end_time":"6.48","alternatives":[{"confidence":"1.0","content":"doing"}],"type":"pronunciation"},{"start_time":"6.48","end_time":"6.6","alternatives":[{"confidence":"0.9999","content":"it"}],"type":"pronunciation"},{"alternatives":[{"confidence":"0.0","content":"."}],"type":"punctuation"}]},"status":"COMPLETED"}