{"jobName":"mix80_original_1","accountId":"821883008341","results":{"transcripts":[{"transcript":"And uh and I talked to actually talked this out with Millie Gussie, who was the casting director at paramount."}],"items":[{"start_time":"0.0","end_time":"0.33","alternatives":[{"confidence":"1.0","content":"And"}],"type":"pronunciation"},{"start_time":"0.33","end_time":"0.53","alternatives":[{"confidence":"0.9929","content":"uh"}],"type":"pronunciation"},{"start_time":"0.53","end_time":"0.74","alternatives":[{"confidence":"0.9996","content":"and"}],"type":"pronunciation"},{"start_time":"0.74","end_time":"0.81","alternatives":[{"confidence":"1.0","content":"I"}],"type":"pronunciation"},{"start_time":"0.81","end_time":"1.28","alternatives":[{"confidence":"0.9852","content":"talked"}],"type":"pronunciation"},{"start_time":"1.28","end_time":"1.53","alternatives":[{"confidence":"0.9978","content":"to"}],"type":"pronunciation"},{"start_time":"1.53","end_time":"2.3","alternatives":[{"confidence":"1.0","content":"actually"}],"type":"pronunciation"},{"start_time":"2.33","end_time":"2.87","alternatives":[{"confidence":"0.4283","content":"talked"}],"type":"pronunciation"},{"start_time":"2.87","end_time":"3.1","alternatives":[{"confidence":"1.0","content":"this"}],"type":"pronunciation"},{"start_time":"3.1","end_time":"3.32","alternatives":[{"confidence":"1.0","content":"out"}],"type":"pronunciation"},{"start_time":"3.32","end_time":"3.53","alternatives":[{"confidence":"1.0","content":"with"}],"type":"pronunciation"},{"start_time":"3.53","end_time":"3.81","alternatives":[{"confidence":"0.5315","content":"Millie"}],"type":"pronunciation"},{"start_time":"3.81","end_time":"4.29","alternatives":[{"confidence":"0.5089","content":"Gussie"}],"type":"pronunciation"},{"alternatives":[{"confidence":"0.0","content":","}],"type":"punctuation"},{"start_time":"4.29","end_time":"4.47","alternatives":[{"confidence":"1.0","content":"who"}],"type":"pronunciation"},{"start_time":"4.47","end_time":"4.84","alternatives":[{"confidence":"1.0","content":"was"}],"type":"pronunciation"},{"start_time":"4.85","end_time":"5.33","alternatives":[{"confidence":"1.0","content":"the"}],"type":"pronunciation"},{"start_time":"5.34","end_time":"5.94","alternatives":[{"confidence":"1.0","content":"casting"}],"type":"pronunciation"},{"start_time":"5.94","end_time":"6.44","alternatives":[{"confidence":"1.0","content":"director"}],"type":"pronunciation"},{"start_time":"6.44","end_time":"6.57","alternatives":[{"confidence":"0.7683","content":"at"}],"type":"pronunciation"},{"start_time":"6.57","end_time":"7.08","alternatives":[{"confidence":"1.0","content":"paramount"}],"type":"pronunciation"},{"alternatives":[{"confidence":"0.0","content":"."}],"type":"punctuation"}]},"status":"COMPLETED"}