{"jobName":"mix104_separation_2","accountId":"821883008341","results":{"transcripts":[{"transcript":"you know, a draw mature if you will on set to make sure that we got it right. And if we didn't get it right, believe"}],"items":[{"start_time":"0.14","end_time":"0.32","alternatives":[{"confidence":"1.0","content":"you"}],"type":"pronunciation"},{"start_time":"0.32","end_time":"0.47","alternatives":[{"confidence":"1.0","content":"know"}],"type":"pronunciation"},{"alternatives":[{"confidence":"0.0","content":","}],"type":"punctuation"},{"start_time":"0.47","end_time":"0.61","alternatives":[{"confidence":"1.0","content":"a"}],"type":"pronunciation"},{"start_time":"0.61","end_time":"0.85","alternatives":[{"confidence":"1.0","content":"draw"}],"type":"pronunciation"},{"start_time":"0.85","end_time":"1.35","alternatives":[{"confidence":"1.0","content":"mature"}],"type":"pronunciation"},{"start_time":"1.35","end_time":"1.49","alternatives":[{"confidence":"1.0","content":"if"}],"type":"pronunciation"},{"start_time":"1.49","end_time":"1.61","alternatives":[{"confidence":"1.0","content":"you"}],"type":"pronunciation"},{"start_time":"1.61","end_time":"1.9","alternatives":[{"confidence":"1.0","content":"will"}],"type":"pronunciation"},{"start_time":"1.9","end_time":"2.1","alternatives":[{"confidence":"1.0","content":"on"}],"type":"pronunciation"},{"start_time":"2.1","end_time":"2.59","alternatives":[{"confidence":"0.9687","content":"set"}],"type":"pronunciation"},{"start_time":"2.6","end_time":"2.81","alternatives":[{"confidence":"1.0","content":"to"}],"type":"pronunciation"},{"start_time":"2.81","end_time":"3.01","alternatives":[{"confidence":"1.0","content":"make"}],"type":"pronunciation"},{"start_time":"3.01","end_time":"3.18","alternatives":[{"confidence":"1.0","content":"sure"}],"type":"pronunciation"},{"start_time":"3.18","end_time":"3.28","alternatives":[{"confidence":"1.0","content":"that"}],"type":"pronunciation"},{"start_time":"3.28","end_time":"3.42","alternatives":[{"confidence":"1.0","content":"we"}],"type":"pronunciation"},{"start_time":"3.42","end_time":"3.63","alternatives":[{"confidence":"1.0","content":"got"}],"type":"pronunciation"},{"start_time":"3.63","end_time":"3.74","alternatives":[{"confidence":"1.0","content":"it"}],"type":"pronunciation"},{"start_time":"3.74","end_time":"4.25","alternatives":[{"confidence":"1.0","content":"right"}],"type":"pronunciation"},{"alternatives":[{"confidence":"0.0","content":"."}],"type":"punctuation"},{"start_time":"4.51","end_time":"4.78","alternatives":[{"confidence":"1.0","content":"And"}],"type":"pronunciation"},{"start_time":"4.78","end_time":"4.87","alternatives":[{"confidence":"1.0","content":"if"}],"type":"pronunciation"},{"start_time":"4.87","end_time":"4.97","alternatives":[{"confidence":"1.0","content":"we"}],"type":"pronunciation"},{"start_time":"4.97","end_time":"5.21","alternatives":[{"confidence":"1.0","content":"didn't"}],"type":"pronunciation"},{"start_time":"5.21","end_time":"5.34","alternatives":[{"confidence":"1.0","content":"get"}],"type":"pronunciation"},{"start_time":"5.34","end_time":"5.43","alternatives":[{"confidence":"0.9828","content":"it"}],"type":"pronunciation"},{"start_time":"5.43","end_time":"5.68","alternatives":[{"confidence":"1.0","content":"right"}],"type":"pronunciation"},{"alternatives":[{"confidence":"0.0","content":","}],"type":"punctuation"},{"start_time":"5.68","end_time":"6.06","alternatives":[{"confidence":"0.8934","content":"believe"}],"type":"pronunciation"}]},"status":"COMPLETED"}