{"jobName":"mix162_separation_2","accountId":"821883008341","results":{"transcripts":[{"transcript":"when you know when I'm already have to try to kiss me and then I kissed him and it's things like my brother and then you know, this comes and"}],"items":[{"start_time":"0.25","end_time":"0.5","alternatives":[{"confidence":"0.9844","content":"when"}],"type":"pronunciation"},{"start_time":"0.5","end_time":"0.65","alternatives":[{"confidence":"1.0","content":"you"}],"type":"pronunciation"},{"start_time":"0.65","end_time":"0.8","alternatives":[{"confidence":"1.0","content":"know"}],"type":"pronunciation"},{"start_time":"0.8","end_time":"1.25","alternatives":[{"confidence":"1.0","content":"when"}],"type":"pronunciation"},{"start_time":"1.26","end_time":"1.57","alternatives":[{"confidence":"0.7048","content":"I'm"}],"type":"pronunciation"},{"start_time":"1.57","end_time":"1.84","alternatives":[{"confidence":"1.0","content":"already"}],"type":"pronunciation"},{"start_time":"1.84","end_time":"2.0","alternatives":[{"confidence":"0.9635","content":"have"}],"type":"pronunciation"},{"start_time":"2.0","end_time":"2.1","alternatives":[{"confidence":"1.0","content":"to"}],"type":"pronunciation"},{"start_time":"2.1","end_time":"2.29","alternatives":[{"confidence":"1.0","content":"try"}],"type":"pronunciation"},{"start_time":"2.29","end_time":"2.38","alternatives":[{"confidence":"1.0","content":"to"}],"type":"pronunciation"},{"start_time":"2.38","end_time":"2.67","alternatives":[{"confidence":"1.0","content":"kiss"}],"type":"pronunciation"},{"start_time":"2.67","end_time":"3.17","alternatives":[{"confidence":"1.0","content":"me"}],"type":"pronunciation"},{"start_time":"3.17","end_time":"3.3","alternatives":[{"confidence":"1.0","content":"and"}],"type":"pronunciation"},{"start_time":"3.3","end_time":"3.42","alternatives":[{"confidence":"1.0","content":"then"}],"type":"pronunciation"},{"start_time":"3.42","end_time":"3.51","alternatives":[{"confidence":"1.0","content":"I"}],"type":"pronunciation"},{"start_time":"3.51","end_time":"3.8","alternatives":[{"confidence":"0.9778","content":"kissed"}],"type":"pronunciation"},{"start_time":"3.8","end_time":"4.28","alternatives":[{"confidence":"1.0","content":"him"}],"type":"pronunciation"},{"start_time":"4.28","end_time":"4.46","alternatives":[{"confidence":"1.0","content":"and"}],"type":"pronunciation"},{"start_time":"4.46","end_time":"4.72","alternatives":[{"confidence":"0.8198","content":"it's"}],"type":"pronunciation"},{"start_time":"4.73","end_time":"5.33","alternatives":[{"confidence":"1.0","content":"things"}],"type":"pronunciation"},{"start_time":"5.33","end_time":"5.47","alternatives":[{"confidence":"1.0","content":"like"}],"type":"pronunciation"},{"start_time":"5.47","end_time":"5.59","alternatives":[{"confidence":"1.0","content":"my"}],"type":"pronunciation"},{"start_time":"5.59","end_time":"6.26","alternatives":[{"confidence":"1.0","content":"brother"}],"type":"pronunciation"},{"start_time":"6.26","end_time":"6.37","alternatives":[{"confidence":"1.0","content":"and"}],"type":"pronunciation"},{"start_time":"6.37","end_time":"6.65","alternatives":[{"confidence":"1.0","content":"then"}],"type":"pronunciation"},{"start_time":"7.02","end_time":"7.3","alternatives":[{"confidence":"1.0","content":"you"}],"type":"pronunciation"},{"start_time":"7.3","end_time":"7.49","alternatives":[{"confidence":"1.0","content":"know"}],"type":"pronunciation"},{"alternatives":[{"confidence":"0.0","content":","}],"type":"punctuation"},{"start_time":"7.49","end_time":"7.89","alternatives":[{"confidence":"0.9827","content":"this"}],"type":"pronunciation"},{"start_time":"7.89","end_time":"8.42","alternatives":[{"confidence":"0.9831","content":"comes"}],"type":"pronunciation"},{"start_time":"8.42","end_time":"8.9","alternatives":[{"confidence":"0.9999","content":"and"}],"type":"pronunciation"}]},"status":"COMPLETED"}