{"jobName":"mix148_separation_1","accountId":"821883008341","results":{"transcripts":[{"transcript":"Hubbard watch the new bar, you know, a regular bar, a neighborly bar, the kind of bar where people go when they're feeling down and out when they've lost their job. And they really want to lose themselves."}],"items":[{"start_time":"0.0","end_time":"0.48","alternatives":[{"confidence":"0.7687","content":"Hubbard"}],"type":"pronunciation"},{"start_time":"0.48","end_time":"0.66","alternatives":[{"confidence":"0.6399","content":"watch"}],"type":"pronunciation"},{"start_time":"0.66","end_time":"0.75","alternatives":[{"confidence":"0.941","content":"the"}],"type":"pronunciation"},{"start_time":"0.75","end_time":"1.01","alternatives":[{"confidence":"0.7235","content":"new"}],"type":"pronunciation"},{"start_time":"1.01","end_time":"1.53","alternatives":[{"confidence":"0.8027","content":"bar"}],"type":"pronunciation"},{"alternatives":[{"confidence":"0.0","content":","}],"type":"punctuation"},{"start_time":"1.86","end_time":"2.0","alternatives":[{"confidence":"1.0","content":"you"}],"type":"pronunciation"},{"start_time":"2.0","end_time":"2.16","alternatives":[{"confidence":"1.0","content":"know"}],"type":"pronunciation"},{"alternatives":[{"confidence":"0.0","content":","}],"type":"punctuation"},{"start_time":"2.16","end_time":"2.52","alternatives":[{"confidence":"1.0","content":"a"}],"type":"pronunciation"},{"start_time":"2.52","end_time":"2.91","alternatives":[{"confidence":"1.0","content":"regular"}],"type":"pronunciation"},{"start_time":"2.91","end_time":"3.21","alternatives":[{"confidence":"0.9951","content":"bar"}],"type":"pronunciation"},{"alternatives":[{"confidence":"0.0","content":","}],"type":"punctuation"},{"start_time":"3.21","end_time":"3.35","alternatives":[{"confidence":"0.9908","content":"a"}],"type":"pronunciation"},{"start_time":"3.35","end_time":"3.84","alternatives":[{"confidence":"0.8711","content":"neighborly"}],"type":"pronunciation"},{"start_time":"3.84","end_time":"4.1","alternatives":[{"confidence":"0.9487","content":"bar"}],"type":"pronunciation"},{"alternatives":[{"confidence":"0.0","content":","}],"type":"punctuation"},{"start_time":"4.1","end_time":"4.2","alternatives":[{"confidence":"0.8976","content":"the"}],"type":"pronunciation"},{"start_time":"4.2","end_time":"4.42","alternatives":[{"confidence":"1.0","content":"kind"}],"type":"pronunciation"},{"start_time":"4.42","end_time":"4.49","alternatives":[{"confidence":"1.0","content":"of"}],"type":"pronunciation"},{"start_time":"4.49","end_time":"4.81","alternatives":[{"confidence":"0.9965","content":"bar"}],"type":"pronunciation"},{"start_time":"4.81","end_time":"4.94","alternatives":[{"confidence":"1.0","content":"where"}],"type":"pronunciation"},{"start_time":"4.94","end_time":"5.23","alternatives":[{"confidence":"1.0","content":"people"}],"type":"pronunciation"},{"start_time":"5.23","end_time":"5.49","alternatives":[{"confidence":"1.0","content":"go"}],"type":"pronunciation"},{"start_time":"5.49","end_time":"5.63","alternatives":[{"confidence":"1.0","content":"when"}],"type":"pronunciation"},{"start_time":"5.63","end_time":"5.77","alternatives":[{"confidence":"0.997","content":"they're"}],"type":"pronunciation"},{"start_time":"5.77","end_time":"6.16","alternatives":[{"confidence":"1.0","content":"feeling"}],"type":"pronunciation"},{"start_time":"6.16","end_time":"6.49","alternatives":[{"confidence":"1.0","content":"down"}],"type":"pronunciation"},{"start_time":"6.49","end_time":"6.64","alternatives":[{"confidence":"1.0","content":"and"}],"type":"pronunciation"},{"start_time":"6.64","end_time":"7.0","alternatives":[{"confidence":"1.0","content":"out"}],"type":"pronunciation"},{"start_time":"7.03","end_time":"7.24","alternatives":[{"confidence":"1.0","content":"when"}],"type":"pronunciation"},{"start_time":"7.24","end_time":"7.39","alternatives":[{"confidence":"0.9926","content":"they've"}],"type":"pronunciation"},{"start_time":"7.39","end_time":"7.63","alternatives":[{"confidence":"0.9928","content":"lost"}],"type":"pronunciation"},{"start_time":"7.63","end_time":"7.77","alternatives":[{"confidence":"1.0","content":"their"}],"type":"pronunciation"},{"start_time":"7.77","end_time":"8.07","alternatives":[{"confidence":"0.9915","content":"job"}],"type":"pronunciation"},{"alternatives":[{"confidence":"0.0","content":"."}],"type":"punctuation"},{"start_time":"8.07","end_time":"8.16","alternatives":[{"confidence":"1.0","content":"And"}],"type":"pronunciation"},{"start_time":"8.16","end_time":"8.3","alternatives":[{"confidence":"1.0","content":"they"}],"type":"pronunciation"},{"start_time":"8.3","end_time":"8.58","alternatives":[{"confidence":"1.0","content":"really"}],"type":"pronunciation"},{"start_time":"8.58","end_time":"8.72","alternatives":[{"confidence":"0.8911","content":"want"}],"type":"pronunciation"},{"start_time":"8.72","end_time":"8.78","alternatives":[{"confidence":"0.8911","content":"to"}],"type":"pronunciation"},{"start_time":"8.78","end_time":"8.97","alternatives":[{"confidence":"1.0","content":"lose"}],"type":"pronunciation"},{"start_time":"8.97","end_time":"9.42","alternatives":[{"confidence":"1.0","content":"themselves"}],"type":"pronunciation"},{"alternatives":[{"confidence":"0.0","content":"."}],"type":"punctuation"}]},"status":"COMPLETED"}