{"jobName":"mix65_separation_1","accountId":"821883008341","results":{"transcripts":[{"transcript":"you know, that film rang true for so many people, you know, over three generations. So they remember all those lines and and Rambo, They remember all the action."}],"items":[{"start_time":"0.0","end_time":"0.08","alternatives":[{"confidence":"1.0","content":"you"}],"type":"pronunciation"},{"start_time":"0.08","end_time":"0.45","alternatives":[{"confidence":"0.9982","content":"know"}],"type":"pronunciation"},{"alternatives":[{"confidence":"0.0","content":","}],"type":"punctuation"},{"start_time":"0.87","end_time":"1.35","alternatives":[{"confidence":"1.0","content":"that"}],"type":"pronunciation"},{"start_time":"1.35","end_time":"1.63","alternatives":[{"confidence":"0.9967","content":"film"}],"type":"pronunciation"},{"start_time":"1.63","end_time":"2.24","alternatives":[{"confidence":"0.664","content":"rang"}],"type":"pronunciation"},{"start_time":"2.48","end_time":"3.02","alternatives":[{"confidence":"0.9918","content":"true"}],"type":"pronunciation"},{"start_time":"3.02","end_time":"3.16","alternatives":[{"confidence":"1.0","content":"for"}],"type":"pronunciation"},{"start_time":"3.16","end_time":"3.33","alternatives":[{"confidence":"1.0","content":"so"}],"type":"pronunciation"},{"start_time":"3.33","end_time":"3.52","alternatives":[{"confidence":"1.0","content":"many"}],"type":"pronunciation"},{"start_time":"3.52","end_time":"4.12","alternatives":[{"confidence":"1.0","content":"people"}],"type":"pronunciation"},{"alternatives":[{"confidence":"0.0","content":","}],"type":"punctuation"},{"start_time":"4.34","end_time":"4.53","alternatives":[{"confidence":"1.0","content":"you"}],"type":"pronunciation"},{"start_time":"4.53","end_time":"4.67","alternatives":[{"confidence":"1.0","content":"know"}],"type":"pronunciation"},{"alternatives":[{"confidence":"0.0","content":","}],"type":"punctuation"},{"start_time":"4.67","end_time":"5.02","alternatives":[{"confidence":"1.0","content":"over"}],"type":"pronunciation"},{"start_time":"5.03","end_time":"5.64","alternatives":[{"confidence":"1.0","content":"three"}],"type":"pronunciation"},{"start_time":"5.64","end_time":"6.31","alternatives":[{"confidence":"1.0","content":"generations"}],"type":"pronunciation"},{"alternatives":[{"confidence":"0.0","content":"."}],"type":"punctuation"},{"start_time":"6.74","end_time":"6.96","alternatives":[{"confidence":"1.0","content":"So"}],"type":"pronunciation"},{"start_time":"6.96","end_time":"7.1","alternatives":[{"confidence":"1.0","content":"they"}],"type":"pronunciation"},{"start_time":"7.1","end_time":"7.46","alternatives":[{"confidence":"1.0","content":"remember"}],"type":"pronunciation"},{"start_time":"7.46","end_time":"7.59","alternatives":[{"confidence":"1.0","content":"all"}],"type":"pronunciation"},{"start_time":"7.59","end_time":"7.82","alternatives":[{"confidence":"1.0","content":"those"}],"type":"pronunciation"},{"start_time":"7.82","end_time":"8.27","alternatives":[{"confidence":"1.0","content":"lines"}],"type":"pronunciation"},{"start_time":"8.27","end_time":"8.54","alternatives":[{"confidence":"1.0","content":"and"}],"type":"pronunciation"},{"start_time":"8.97","end_time":"9.26","alternatives":[{"confidence":"1.0","content":"and"}],"type":"pronunciation"},{"start_time":"9.26","end_time":"9.57","alternatives":[{"confidence":"0.9936","content":"Rambo"}],"type":"pronunciation"},{"alternatives":[{"confidence":"0.0","content":","}],"type":"punctuation"},{"start_time":"9.57","end_time":"9.67","alternatives":[{"confidence":"0.987","content":"They"}],"type":"pronunciation"},{"start_time":"9.67","end_time":"10.0","alternatives":[{"confidence":"1.0","content":"remember"}],"type":"pronunciation"},{"start_time":"10.0","end_time":"10.08","alternatives":[{"confidence":"1.0","content":"all"}],"type":"pronunciation"},{"start_time":"10.08","end_time":"10.24","alternatives":[{"confidence":"1.0","content":"the"}],"type":"pronunciation"},{"start_time":"10.24","end_time":"10.73","alternatives":[{"confidence":"0.5209","content":"action"}],"type":"pronunciation"},{"alternatives":[{"confidence":"0.0","content":"."}],"type":"punctuation"}]},"status":"COMPLETED"}